Workbook

Sheet Ingredientes
B4: Ingredientes | C4: Embalagem Fechada (g) | D4: Valor Fechado
B5: ='Custo Unitário'!B70 -> Caldo Verde | C5: 1000 | D5: 25
B6: Tomate | C6: 1000 | D6: =

Sheet Custo Unitário
B4: Frango | C4: Ingredientes | D4: Quantidade (g) | E4: Quantidade da Embalagem (g) | F4: Preço Fechado | G4: Custo Proporcional
E5: =IF(C5="","",VLOOKUP(C5,Ingredientes!B:C,2,0)) | F5: =IF(C5="","",VLOOKUP(C5,Ingredientes!B:E,3,0)) | G5: =IF(C5="","",F5/E5*D5) | I5: Custo por unidade | J5: =IF(G5="","",SUM(G5:G18))
E6: =IF(C6="","",VLOOKUP(C6,Ingredientes!B:C,2,0)) | F6: =IF(C6="","",VLOOKUP(C6,Ingredientes!B:E,3,0)) | G6: =IF(C6="","",F6/E6*D6) | I6: Preço de venda
E7: =IF(C7="","",VLOOKUP(C7,Ingredientes!B:C,2,0)) | F7: =IF(C7="","",VLOOKUP(C7,Ingredientes!B:E,3,0)) | G7: =IF(C7="","",F7/E7*D7) | I7: Lucro | J7: =IF(J6="","",J6-J5)
E8: =IF(C8="","",VLOOKUP(C8,Ingredientes!B:C,2,0)) | F8: =IF(C8="","",VLOOKUP(C8,Ingredientes!B:E,3,0)) | G8: =IF(C8="","",F8/E8*D8) | I8: Lucro % | J8: =IF(J7="","",J7/J5)
E9: =IF(C9="","",VLOOKUP(C9,Ingredientes!B:C,2,0)) | F9: =IF(C9="","",VLOOKUP(C9,Ingredientes!B:E,3,0)) | G9: =IF(C9="","",F9/E9*D9) | I9: Meta %
E10: =IF(C10="","",VLOOKUP(C10,Ingredientes!B:C,2,0)) | F10: =IF(C10="","",VLOOKUP(C10,Ingredientes!B:E,3,0)) | G10: =IF(C10="","",F10/E10*D10) | I10: Valor a ser vendido estimado | J10: =IF(J9="","",(J5*J9)+J5)
E11: =IF(C11="","",VLOOKUP(C11,Ingredientes!B:C,2,0)) | F11: =IF(C11="","",VLOOKUP(C11,Ingredientes!B:E,3,0)) | G11: =IF(C11="","",F11/E11*D11)
E12: =IF(C12="","",VLOOKUP(C12,Ingredientes!B:C,2,0)) | F12: =IF(C12="","",VLOOKUP(C12,Ingredientes!B:E,3,0)) | G12: =IF(C12="","",F12/E12*D12)
E13: =IF(C13="","",VLOOKUP(C13,Ingredientes!B:C,2,0)) | F13: =IF(C13="","",VLOOKUP(C13,Ingredientes!B:E,3,0)) | G13: =IF(C13="","",F13/E13*D13)
E14: =IF(C14="","",VLOOKUP(C14,Ingredientes!B:C,2,0)) | F14: =IF(C14="","",VLOOKUP(C14,Ingredientes!B:E,3,0)) | G14: =IF(C14="","",F14/E14*D14)
E15: =IF(C15="","",VLOOKUP(C15,Ingredientes!B:C,2,0)) | F15: =IF(C15="","",VLOOKUP(C15,Ingredientes!B:E,3,0)) | G15: =IF(C15="","",F15/E15*D15)
E16: =IF(C16="","",VLOOKUP(C16,Ingredientes!B:C,2,0)) | F16: =IF(C16="","",VLOOKUP(C16,Ingredientes!B:E,3,0)) | G16: =IF(C16="","",F16/E16*D16)
E17: =IF(C17="","",VLOOKUP(C17,Ingredientes!B:C,2,0)) | F17: =IF(C17="","",VLOOKUP(C17,Ingredientes!B:E,3,0)) | G17: =IF(C17="","",F17/E17*D17)
E18: =IF(C18="","",VLOOKUP(C18,Ingredientes!B:C,2,0)) | F18: =IF(C18="","",VLOOKUP(C18,Ingredientes!B:E,3,0)) | G18: =IF(C18="","",F18/E18*D18)
B20: Frango Rústico | C20: Ingredientes | D20: Quantidade | E20: Quantidade da Embalagem | F20: Preço Fechado | G20: Custo Proporcional
E21: =IF(C21="","",VLOOKUP(C21,Ingredientes!B:C,2,0)) | F21: =IF(C21="","",VLOOKUP(C21,Ingredientes!B:E,3,0)) | G21: =IF(C21="","",F21/E21*D21) | I21: Custo por unidade | J21: =IF(G21="","",SUM(G21:G34))
E22: =IF(C22="","",VLOOKUP(C22,Ingredientes!B:C,2,0)) | F22: =IF(C22="","",VLOOKUP(C22,Ingredientes!B:E,3,0)) | G22: =IF(C22="","",F22/E22*D22) | I22: Preço de venda
E23: =IF(C23="","",VLOOKUP(C23,Ingredientes!B:C,2,0)) | F23: =IF(C23="","",VLOOKUP(C23,Ingredientes!B:E,3,0)) | G23: =IF(C23="","",F23/E23*D23) | I23: Lucro | J23: =IF(J22="","",J22-J21)
E24: =IF(C24="","",VLOOKUP(C24,Ingredientes!B:C,2,0)) | F24: =IF(C24="","",VLOOKUP(C24,Ingredientes!B:E,3,0)) | G24: =IF(C24="","",F24/E24*D24) | I24: Lucro % | J24: =IF(J23="","",J23/J21)
E25: =IF(C25="","",VLOOKUP(C25,Ingredientes!B:C,2,0)) | F25: =IF(C25="","",VLOOKUP(C25,Ingredientes!B:E,3,0)) | G25: =IF(C25="","",F25/E25*D25) | I25: Meta %
E26: =IF(C26="","",VLOOKUP(C26,Ingredientes!B:C,2,0)) | F26: =IF(C26="","",VLOOKUP(C26,Ingredientes!B:E,3,0)) | G26: =IF(C26="","",F26/E26*D26) | I26: Valor a ser vendido estimado | J26: =IF(J25="","",(J21*J25)+J21)
E27: =IF(C27="","",VLOOKUP(C27,Ingredientes!B:C,2,0)) | F27: =IF(C27="","",VLOOKUP(C27,Ingredientes!B:E,3,0)) | G27: =IF(C27="","",F27/E27*D27)
E28: =IF(C28="","",VLOOKUP(C28,Ingredientes!B:C,2,0)) | F28: =IF(C28="","",VLOOKUP(C28,Ingredientes!B:E,3,0)) | G28: =IF(C28="","",F28/E28*D28)
E29: =IF(C29="","",VLOOKUP(C29,Ingredientes!B:C,2,0)) | F29: =IF(C29="","",VLOOKUP(C29,Ingredientes!B:E,3,0)) | G29: =IF(C29="","",F29/E29*D29)
E30: =IF(C30="","",VLOOKUP(C30,Ingredientes!B:C,2,0)) | F30: =IF(C30="","",VLOOKUP(C30,Ingredientes!B:E,3,0)) | G30: =IF(C30="","",F30/E30*D30)
E31: =IF(C31="","",VLOOKUP(C31,Ingredientes!B:C,2,0)) | F31: =IF(C31="","",VLOOKUP(C31,Ingredientes!B:E,3,0)) | G31: =IF(C31="","",F31/E31*D31)
E32: =IF(C32="","",VLOOKUP(C32,Ingredientes!B:C,2,0)) | F32: =IF(C32="","",VLOOKUP(C32,Ingredientes!B:E,3,0)) | G32: =IF(C32="","",F32/E32*D32)
E33: =IF(C33="","",VLOOKUP(C33,Ingredientes!B:C,2,0)) | F33: =IF(C33="","",VLOOKUP(C33,Ingredientes!B:E,3,0)) | G33: =IF(C33="","",F33/E33*D33)
E34: =IF(C34="","",VLOOKUP(C34,Ingredientes!B:C,2,0)) | F34: =IF(C34="","",VLOOKUP(C34,Ingredientes!B:E,3,0)) | G34: =IF(C34="","",F34/E34*D34)
E35: =IF(C35="","",VLOOKUP(C35,Ingredientes!B:C,2,0)) | F35: =IF(C35="","",VLOOKUP(C35,Ingredientes!B:E,3,0)) | G35: =IF(C35="","",F35/E35*D35)
B37: Carne Louca | C37: Ingredientes | D37: Quantidade | E37: Quantidade da Embalagem | F37: Preço Fechado | G37: Custo Proporcional
E38: =IF(C38="","",VLOOKUP(C38,Ingredientes!B:C,2,0)) | F38: =IF(C38="","",VLOOKUP(C38,Ingredientes!B:E,3,0)) | G38: =IF(C38="","",F38/E38*D38) | I38: Custo por unidade | J38: =IF(G38="","",SUM(G38:G51))
E39: =IF(C39="","",VLOOKUP(C39,Ingredientes!B:C,2,0)) | F39: =IF(C39="","",VLOOKUP(C39,Ingredientes!B:E,3,0)) | G39: =IF(C39="","",F39/E39*D39) | I39: Preço de venda
E40: =IF(C40="","",VLOOKUP(C40,Ingredientes!B:C,2,0)) | F40: =IF(C40="","",VLOOKUP(C40,Ingredientes!B:E,3,0)) | G40: =IF(C40="","",F40/E40*D40) | I40: Lucro | J40: =IF(J39="","",J39-J38)
E41: =IF(C41="","",VLOOKUP(C41,Ingredientes!B:C,2,0)) | F41: =IF(C41="","",VLOOKUP(C41,Ingredientes!B:E,3,0)) | G41: =IF(C41="","",F41/E41*D41) | I41: Lucro % | J41: =IF(J40="","",J40/J38)
E42: =IF(C42="","",VLOOKUP(C42,Ingredientes!B:C,2,0)) | F42: =IF(C42="","",VLOOKUP(C42,Ingredientes!B:E,3,0)) | G42: =IF(C42="","",F42/E42*D42) | I42: Meta %
E43: =IF(C43="","",VLOOKUP(C43,Ingredientes!B:C,2,0)) | F43: =IF(C43="","",VLOOKUP(C43,Ingredientes!B:E,3,0)) | G43: =IF(C43="","",F43/E43*D43) | I43: Valor a ser vendido estimado | J43: =IF(J42="","",(J38*J42)+J38)
E44: =IF(C44="","",VLOOKUP(C44,Ingredientes!B:C,2,0)) | F44: =IF(C44="","",VLOOKUP(C44,Ingredientes!B:E,3,0)) | G44: =IF(C44="","",F44/E44*D44)
E45: =IF(C45="","",VLOOKUP(C45,Ingredientes!B:C,2,0)) | F45: =IF(C45="","",VLOOKUP(C45,Ingredientes!B:E,3,0)) | G45: =IF(C45="","",F45/E45*D45)
E46: =IF(C46="","",VLOOKUP(C46,Ingredientes!B:C,2,0)) | F46: =IF(C46="","",VLOOKUP(C46,Ingredientes!B:E,3,0)) | G46: =IF(C46="","",F46/E46*D46)
E47: =IF(C47="","",VLOOKUP(C47,Ingredientes!B:C,2,0)) | F47: =IF(C47="","",VLOOKUP(C47,Ingredientes!B:E,3,0)) | G47: =IF(C47="","",F47/E47*D47)
E48: =IF(C48="","",VLOOKUP(C48,Ingredientes!B:C,2,0)) | F48: =IF(C48="","",VLOOKUP(C48,Ingredientes!B:E,3,0)) | G48: =IF(C48="","",F48/E48*D48)
E49: =IF(C49="","",VLOOKUP(C49,Ingredientes!B:C,2,0)) | F49: =IF(C49="","",VLOOKUP(C49,Ingredientes!B:E,3,0)) | G49: =IF(C49="","",F49/E49*D49)
E50: =IF(C50="","",VLOOKUP(C50,Ingredientes!B:C,2,0)) | F50: =IF(C50="","",VLOOKUP(C50,Ingredientes!B:E,3,0)) | G50: =IF(C50="","",F50/E50*D50)
E51: =IF(C51="","",VLOOKUP(C51,Ingredientes!B:C,2,0)) | F51: =IF(C51="","",VLOOKUP(C51,Ingredientes!B:E,3,0)) | G51: =IF(C51="","",F51/E51*D51)
E52: =IF(C52="","",VLOOKUP(C52,Ingredientes!B:C,2,0)) | F52: =IF(C52="","",VLOOKUP(C52,Ingredientes!B:E,3,0)) | G52: =IF(C52="","",F52/E52*D52)
B54: Camarão | C54: Ingredientes | D54: Quantidade | E54: Quantidade da Embalagem | F54: Preço Fechado | G54: Custo Proporcional
E55: =IF(C55="","",VLOOKUP(C55,Ingredientes!B:C,2,0)) | F55: =IF(C55="","",VLOOKUP(C55,Ingredientes!B:E,3,0)) | G55: =IF(C55="","",F55/E55*D55) | I55: Custo por unidade | J55: =IF(G55="","",SUM(G55:G68))
E56: =IF(C56="","",VLOOKUP(C56,Ingredientes!B:C,2,0)) | F56: =IF(C56="","",VLOOKUP(C56,Ingredientes!B:E,3,0)) | G56: =IF(C56="","",F56/E56*D56) | I56: Preço de venda
E57: =IF(C57="","",VLOOKUP(C57,Ingredientes!B:C,2,0)) | F57: =IF(C57="","",VLOOKUP(C57,Ingredientes!B:E,3,0)) | G57: =IF(C57="","",F57/E57*D57) | I57: Lucro | J57: =IF(J56="","",J56-J55)
E58: =IF(C58="","",VLOOKUP(C58,Ingredientes!B:C,2,0)) | F58: =IF(C58="","",VLOOKUP(C58,Ingredientes!B:E,3,0)) | G58: =IF(C58="","",F58/E58*D58) | I58: Lucro % | J58: =IF(J57="","",J57/J55)
E59: =IF(C59="","",VLOOKUP(C59,Ingredientes!B:C,2,0)) | F59: =IF(C59="","",VLOOKUP(C59,Ingredientes!B:E,3,0)) | G59: =IF(C59="","",F59/E59*D59) | I59: Meta %
E60: =IF(C60="","",VLOOKUP(C60,Ingredientes!B:C,2,0)) | F60: =IF(C60="","",VLOOKUP(C60,Ingredientes!B:E,3,0)) | G60: =IF(C60="","",F60/E60*D60) | I60: Valor a ser vendido estimado | J60: =IF(J59="","",(J55*J59)+J55)
E61: =IF(C61="","",VLOOKUP(C61,Ingredientes!B:C,2,0)) | F61: =IF(C61="","",VLOOKUP(C61,Ingredientes!B:E,3,0)) | G61: =IF(C61="","",F61/E61*D61)
E62: =IF(C62="","",VLOOKUP(C62,Ingredientes!B:C,2,0)) | F62: =IF(C62="","",VLOOKUP(C62,Ingredientes!B:E,3,0)) | G62: =IF(C62="","",F62/E62*D62)
E63: =IF(C63="","",VLOOKUP(C63,Ingredientes!B:C,2,0)) | F63: =IF(C63="","",VLOOKUP(C63,Ingredientes!B:E,3,0)) | G63: =IF(C63="","",F63/E63*D63)
E64: =IF(C64="","",VLOOKUP(C64,Ingredientes!B:C,2,0)) | F64: =IF(C64="","",VLOOKUP(C64,Ingredientes!B:E,3,0)) | G64: =IF(C64="","",F64/E64*D64)
E65: =IF(C65="","",VLOOKUP(C65,Ingredientes!B:C,2,0)) | F65: =IF(C65="","",VLOOKUP(C65,Ingredientes!B:E,3,0)) | G65: =IF(C65="","",F65/E65*D65)
E66: =IF(C66="","",VLOOKUP(C66,Ingredientes!B:C,2,0)) | F66: =IF(C66="","",VLOOKUP(C66,Ingredientes!B:E,3,0)) | G66: =IF(C66="","",F66/E66*D66)
E67: =IF(C67="","",VLOOKUP(C67,Ingredientes!B:C,2,0)) | F67: =IF(C67="","",VLOOKUP(C67,Ingredientes!B:E,3,0)) | G67: =IF(C67="","",F67/E67*D67)
E68: =IF(C68="","",VLOOKUP(C68,Ingredientes!B:C,2,0)) | F68: =IF(C68="","",VLOOKUP(C68,Ingredientes!B:E,3,0)) | G68: =IF(C68="","",F68/E68*D68)
B70: Caldo Verde | C70: Ingredientes | D70: Quantidade | E70: Quantidade da Embalagem | F70: Preço Fechado | G70: Custo Proporcional
E71: =IF(C71="","",VLOOKUP(C71,Ingredientes!B:C,2,0)) | F71: =IF(C71="","",VLOOKUP(C71,Ingredientes!B:E,3,0)) | G71: =IF(C71="","",F71/E71*D71) | I71: Custo por unidade | J71: =IF(G71="","",SUM(G71:G84))
E72: =IF(C72="","",VLOOKUP(C72,Ingredientes!B:C,2,0)) | F72: =IF(C72="","",VLOOKUP(C72,Ingredientes!B:E,3,0)) | G72: =IF(C72="","",F72/E72*D72) | I72: Preço de venda
E73: =IF(C73="","",VLOOKUP(C73,Ingredientes!B:C,2,0)) | F73: =IF(C73="","",VLOOKUP(C73,Ingredientes!B:E,3,0)) | G73: =IF(C73="","",F73/E73*D73) | I73: Lucro | J73: =IF(J72="","",J72-J71)
E74: =IF(C74="","",VLOOKUP(C74,Ingredientes!B:C,2,0)) | F74: =IF(C74="","",VLOOKUP(C74,Ingredientes!B:E,3,0)) | G74: =IF(C74="","",F74/E74*D74) | I74: Lucro % | J74: =IF(J73="","",J73/J71)
E75: =IF(C75="","",VLOOKUP(C75,Ingredientes!B:C,2,0)) | F75: =IF(C75="","",VLOOKUP(C75,Ingredientes!B:E,3,0)) | G75: =IF(C75="","",F75/E75*D75) | I75: Meta %
E76: =IF(C76="","",VLOOKUP(C76,Ingredientes!B:C,2,0)) | F76: =IF(C76="","",VLOOKUP(C76,Ingredientes!B:E,3,0)) | G76: =IF(C76="","",F76/E76*D76) | I76: Valor a ser vendido estimado | J76: =IF(J75="","",(J71*J75)+J71)
E77: =IF(C77="","",VLOOKUP(C77,Ingredientes!B:C,2,0)) | F77: =IF(C77="","",VLOOKUP(C77,Ingredientes!B:E,3,0)) | G77: =IF(C77="","",F77/E77*D77)
E78: =IF(C78="","",VLOOKUP(C78,Ingredientes!B:C,2,0)) | F78: =IF(C78="","",VLOOKUP(C78,Ingredientes!B:E,3,0)) | G78: =IF(C78="","",F78/E78*D78)
E79: =IF(C79="","",VLOOKUP(C79,Ingredientes!B:C,2,0)) | F79: =IF(C79="","",VLOOKUP(C79,Ingredientes!B:E,3,0)) | G79: =IF(C79="","",F79/E79*D79)
E80: =IF(C80="","",VLOOKUP(C80,Ingredientes!B:C,2,0)) | F80: =IF(C80="","",VLOOKUP(C80,Ingredientes!B:E,3,0)) | G80: =IF(C80="","",F80/E80*D80)
E81: =IF(C81="","",VLOOKUP(C81,Ingredientes!B:C,2,0)) | F81: =IF(C81="","",VLOOKUP(C81,Ingredientes!B:E,3,0)) | G81: =IF(C81="","",F81/E81*D81)
E82: =IF(C82="","",VLOOKUP(C82,Ingredientes!B:C,2,0)) | F82: =IF(C82="","",VLOOKUP(C82,Ingredientes!B:E,3,0)) | G82: =IF(C82="","",F82/E82*D82)
E83: =IF(C83="","",VLOOKUP(C83,Ingredientes!B:C,2,0)) | F83: =IF(C83="","",VLOOKUP(C83,Ingredientes!B:E,3,0)) | G83: =IF(C83="","",F83/E83*D83)
E84: =IF(C84="","",VLOOKUP(C84,Ingredientes!B:C,2,0)) | F84: =IF(C84="","",VLOOKUP(C84,Ingredientes!B:E,3,0)) | G84: =IF(C84="","",F84/E84*D84)
E85: =IF(C85="","",VLOOKUP(C85,Ingredientes!B:C,2,0)) | F85: =IF(C85="","",VLOOKUP(C85,Ingredientes!B:E,3,0)) | G85: =IF(C85="","",F85/E85*D85)
B87: Bacon c/ Calabresa | C87: Ingredientes | D87: Quantidade | E87: Quantidade da Embalagem | F87: Preço Fechado | G87: Custo Proporcional
E88: =IF(C88="","",VLOOKUP(C88,Ingredientes!B:C,2,0)) | F88: =IF(C88="","",VLOOKUP(C88,Ingredientes!B:E,3,0)) | G88: =IF(C88="","",F88/E88*D88) | I88: Custo por unidade | J88: =IF(G88="","",SUM(G88:G101))
E89: =IF(C89="","",VLOOKUP(C89,Ingredientes!B:C,2,0)) | F89: =IF(C89="","",VLOOKUP(C89,Ingredientes!B:E,3,0)) | G89: =IF(C89="","",F89/E89*D89) | I89: Preço de venda
E90: =IF(C90="","",VLOOKUP(C90,Ingredientes!B:C,2,0)) | F90: =IF(C90="","",VLOOKUP(C90,Ingredientes!B:E,3,0)) | G90: =IF(C90="","",F90/E90*D90) | I90: Lucro | J90: =IF(J89="","",J89-J88)
E91: =IF(C91="","",VLOOKUP(C91,Ingredientes!B:C,2,0)) | F91: =IF(C91="","",VLOOKUP(C91,Ingredientes!B:E,3,0)) | G91: =IF(C91="","",F91/E91*D91) | I91: Lucro % | J91: =IF(J90="","",J90/J88)
E92: =IF(C92="","",VLOOKUP(C92,Ingredientes!B:C,2,0)) | F92: =IF(C92="","",VLOOKUP(C92,Ingredientes!B:E,3,0)) | G92: =IF(C92="","",F92/E92*D92) | I92: Meta %
E93: =IF(C93="","",VLOOKUP(C93,Ingredientes!B:C,2,0)) | F93: =IF(C93="","",VLOOKUP(C93,Ingredientes!B:E,3,0)) | G93: =IF(C93="","",F93/E93*D93) | I93: Valor a ser vendido estimado | J93: =IF(J92="","",(J88*J92)+J88)
E94: =IF(C94="","",VLOOKUP(C94,Ingredientes!B:C,2,0)) | F94: =IF(C94="","",VLOOKUP(C94,Ingredientes!B:E,3,0)) | G94: =IF(C94="","",F94/E94*D94)
E95: =IF(C95="","",VLOOKUP(C95,Ingredientes!B:C,2,0)) | F95: =IF(C95="","",VLOOKUP(C95,Ingredientes!B:E,3,0)) | G95: =IF(C95="","",F95/E95*D95)
E96: =IF(C96="","",VLOOKUP(C96,Ingredientes!B:C,2,0)) | F96: =IF(C96="","",VLOOKUP(C96,Ingredientes!B:E,3,0)) | G96: =IF(C96="","",F96/E96*D96)
E97: =IF(C97="","",VLOOKUP(C97,Ingredientes!B:C,2,0)) | F97: =IF(C97="","",VLOOKUP(C97,Ingredientes!B:E,3,0)) | G97: =IF(C97="","",F97/E97*D97)
E98: =IF(C98="","",VLOOKUP(C98,Ingredientes!B:C,2,0)) | F98: =IF(C98="","",VLOOKUP(C98,Ingredientes!B:E,3,0)) | G98: =IF(C98="","",F98/E98*D98)
E99: =IF(C99="","",VLOOKUP(C99,Ingredientes!B:C,2,0)) | F99: =IF(C99="","",VLOOKUP(C99,Ingredientes!B:E,3,0)) | G99: =IF(C99="","",F99/E99*D99)
E100: =IF(C100="","",VLOOKUP(C100,Ingredientes!B:C,2,0)) | F100: =IF(C100="","",VLOOKUP(C100,Ingredientes!B:E,3,0)) | G100: =IF(C100="","",F100/E100*D100)
E101: =IF(C101="","",VLOOKUP(C101,Ingredientes!B:C,2,0)) | F101: =IF(C101="","",VLOOKUP(C101,Ingredientes!B:E,3,0)) | G101: =IF(C101="","",F101/E101*D101)
